jpt_django_utils/__init__.py
jpt_django_utils/apps.py
jpt_django_utils/exceptions.py
jpt_django_utils/auto_version/__init__.py
jpt_django_utils/auto_version/admin.py
jpt_django_utils/auto_version/fields.py
jpt_django_utils/auto_version/models.py
jpt_django_utils/auto_version/serializers.py
jpt_django_utils/created_updated/__init__.py
jpt_django_utils/created_updated/admin.py
jpt_django_utils/created_updated/models.py
jpt_django_utils/created_updated/serializers.py
jpt_django_utils/publishable/__init__.py
jpt_django_utils/publishable/managers.py
jpt_django_utils/publishable/models.py
jpt_django_utils/rest_framework/__init__.py
jpt_django_utils/rest_framework/exceptions.py
jpt_django_utils/rest_framework/middleware.py
jpt_django_utils/rest_framework/mixins.py
jpt_django_utils/rest_framework/views.py
jpt_django_utils/soft_delete/__init__.py
jpt_django_utils/soft_delete/managers.py
jpt_django_utils/soft_delete/models.py
jpt_django_utils/testing/__init__.py
jpt_django_utils/testing/client.py
jpt_django_utils/testing/fixtures.py
jpt_django_utils-0.8.0.dist-info/DESCRIPTION.rst
jpt_django_utils-0.8.0.dist-info/METADATA
jpt_django_utils-0.8.0.dist-info/RECORD
jpt_django_utils-0.8.0.dist-info/WHEEL
jpt_django_utils-0.8.0.dist-info/metadata.json
jpt_django_utils-0.8.0.dist-info/top_level.txt
