Metadata-Version: 2.0
Name: jpt-django-utils
Version: 0.8.0
Summary: Re-usable Django utils.
Home-page: https://github.com/jptd/JPT-DJANGO-UTILS
Author: Jewel Paymentech
Author-email: jafnee.jesmee@jewelpaymentech.com
License: UNKNOWN
Keywords: jpt-django-utils
Platform: UNKNOWN
Classifier: Development Status :: 3 - Alpha
Classifier: Environment :: Web Environment
Classifier: Intended Audience :: Developers
Classifier: Operating System :: OS Independent
Classifier: Framework :: Django
Classifier: Framework :: Django :: 2.2
Classifier: Natural Language :: English
Classifier: Programming Language :: Python
Classifier: Programming Language :: Python :: 3.6
Classifier: Programming Language :: Python :: 3 :: Only
Classifier: License :: Other/Proprietary License
Requires-Python: >=3.6
